[
    {
        "FullName":  "D:\\temp\\RUCxiaolaba-Advanced-Search\\data\\posts.db",
        "Length":  6287257600,
        "LastWriteTime":  "\/Date(1780325429989)\/"
    },
    {
        "FullName":  "D:\\temp\\RUCxiaolaba-Advanced-Search\\data\\posts.slim.db",
        "Length":  3982770176,
        "LastWriteTime":  "\/Date(1780371420621)\/"
    },
    {
        "FullName":  "D:\\temp\\RUCxiaolaba-Advanced-Search\\data\\posts_final.csv",
        "Length":  2436666503,
        "LastWriteTime":  "\/Date(1780320448958)\/"
    },
    {
        "FullName":  "D:\\temp\\RUCxiaolaba-Advanced-Search\\data\\posts_final.csv.gz",
        "Length":  26304148,
        "LastWriteTime":  "\/Date(1780209912941)\/"
    },
    {
        "FullName":  "D:\\temp\\RUCxiaolaba-Advanced-Search\\data\\config.example.txt",
        "Length":  251,
        "LastWriteTime":  "\/Date(1779967375437)\/"
    },
    {
        "FullName":  "D:\\temp\\RUCxiaolaba-Advanced-Search\\data\\feedback.jsonl",
        "Length":  84,
        "LastWriteTime":  "\/Date(1780164586084)\/"
    },
    {
        "FullName":  "D:\\temp\\RUCxiaolaba-Advanced-Search\\data\\.crawl_checkpoint.json",
        "Length":  75,
        "LastWriteTime":  "\/Date(1780093430915)\/"
    },
    {
        "FullName":  "D:\\temp\\RUCxiaolaba-Advanced-Search\\data\\config.txt",
        "Length":  50,
        "LastWriteTime":  "\/Date(1779967452957)\/"
    },
    {
        "FullName":  "D:\\temp\\RUCxiaolaba-Advanced-Search\\data\\railway_sync\\20260601-203002\\checkin_count.json",
        "Length":  49,
        "LastWriteTime":  "\/Date(1780317015908)\/"
    },
    {
        "FullName":  "D:\\temp\\RUCxiaolaba-Advanced-Search\\data\\railway_sync\\20260602-033350\\checkin_count.json",
        "Length":  49,
        "LastWriteTime":  "\/Date(1780366106102)\/"
    },
    {
        "FullName":  "D:\\temp\\RUCxiaolaba-Advanced-Search\\data\\railway_sync\\20260602-101249\\checkin_count.json",
        "Length":  49,
        "LastWriteTime":  "\/Date(1780366383809)\/"
    },
    {
        "FullName":  "D:\\temp\\RUCxiaolaba-Advanced-Search\\data\\railway_sync\\20260601-194026\\checkin_count.json",
        "Length":  49,
        "LastWriteTime":  "\/Date(1780314050821)\/"
    },
    {
        "FullName":  "D:\\temp\\RUCxiaolaba-Advanced-Search\\data\\railway_sync\\20260602-023001\\checkin_count.json",
        "Length":  49,
        "LastWriteTime":  "\/Date(1780338614119)\/"
    },
    {
        "FullName":  "D:\\temp\\RUCxiaolaba-Advanced-Search\\data\\railway_sync\\20260601-213002\\checkin_count.json",
        "Length":  49,
        "LastWriteTime":  "\/Date(1780320618505)\/"
    },
    {
        "FullName":  "D:\\temp\\RUCxiaolaba-Advanced-Search\\data\\railway_sync\\20260602-013002\\checkin_count.json",
        "Length":  49,
        "LastWriteTime":  "\/Date(1780335016141)\/"
    },
    {
        "FullName":  "D:\\temp\\RUCxiaolaba-Advanced-Search\\data\\railway_sync\\20260601-233001\\checkin_count.json",
        "Length":  49,
        "LastWriteTime":  "\/Date(1780327813628)\/"
    },
    {
        "FullName":  "D:\\temp\\RUCxiaolaba-Advanced-Search\\data\\checkin_count.json",
        "Length":  49,
        "LastWriteTime":  "\/Date(1780178396272)\/"
    },
    {
        "FullName":  "D:\\temp\\RUCxiaolaba-Advanced-Search\\data\\checkin_count.json.tmp",
        "Length":  49,
        "LastWriteTime":  "\/Date(1780178361953)\/"
    },
    {
        "FullName":  "D:\\temp\\RUCxiaolaba-Advanced-Search\\data\\railway_sync\\20260602-113002\\checkin_count.json",
        "Length":  49,
        "LastWriteTime":  "\/Date(1780371015940)\/"
    },
    {
        "FullName":  "D:\\temp\\RUCxiaolaba-Advanced-Search\\data\\railway_sync\\20260601-144828\\checkin_count.json",
        "Length":  49,
        "LastWriteTime":  "\/Date(1780296526103)\/"
    },
    {
        "FullName":  "D:\\temp\\RUCxiaolaba-Advanced-Search\\data\\railway_sync\\20260602-103003\\checkin_count.json",
        "Length":  49,
        "LastWriteTime":  "\/Date(1780367417415)\/"
    },
    {
        "FullName":  "D:\\temp\\RUCxiaolaba-Advanced-Search\\data\\railway_sync\\checkin_count.latest.json",
        "Length":  49,
        "LastWriteTime":  "\/Date(1780371015940)\/"
    },
    {
        "FullName":  "D:\\temp\\RUCxiaolaba-Advanced-Search\\data\\railway_sync\\20260602-003001\\checkin_count.json",
        "Length":  49,
        "LastWriteTime":  "\/Date(1780331416208)\/"
    },
    {
        "FullName":  "D:\\temp\\RUCxiaolaba-Advanced-Search\\data\\railway_sync\\20260601-173002\\checkin_count.json",
        "Length":  49,
        "LastWriteTime":  "\/Date(1780306213655)\/"
    },
    {
        "FullName":  "D:\\temp\\RUCxiaolaba-Advanced-Search\\data\\railway_sync\\20260601-153001\\checkin_count.json",
        "Length":  43,
        "LastWriteTime":  "\/Date(1780299015775)\/"
    },
    {
        "FullName":  "D:\\temp\\RUCxiaolaba-Advanced-Search\\data\\railway_sync\\20260601-163002\\checkin_count.json",
        "Length":  43,
        "LastWriteTime":  "\/Date(1780302614634)\/"
    },
    {
        "FullName":  "D:\\temp\\RUCxiaolaba-Advanced-Search\\data\\railway_sync\\checkin_count.init.json",
        "Length":  43,
        "LastWriteTime":  "\/Date(1780296546149)\/"
    },
    {
        "FullName":  "D:\\temp\\RUCxiaolaba-Advanced-Search\\data\\railway_sync\\20260601-144603\\checkin_count.json",
        "Length":  40,
        "LastWriteTime":  "\/Date(1780296374085)\/"
    },
    {
        "FullName":  "D:\\temp\\RUCxiaolaba-Advanced-Search\\data\\admin_password.txt",
        "Length":  16,
        "LastWriteTime":  "\/Date(1780133413765)\/"
    },
    {
        "FullName":  "D:\\temp\\RUCxiaolaba-Advanced-Search\\data\\railway_sync\\20260601-223002\\checkin_count.json",
        "Length":  16,
        "LastWriteTime":  "\/Date(1780324203584)\/"
    },
    {
        "FullName":  "D:\\temp\\RUCxiaolaba-Advanced-Search\\data\\railway_sync\\20260601-183007\\checkin_count.json",
        "Length":  16,
        "LastWriteTime":  "\/Date(1780309821634)\/"
    },
    {
        "FullName":  "D:\\temp\\RUCxiaolaba-Advanced-Search\\data\\railway_sync\\20260601-183007\\feedback.jsonl",
        "Length":  5,
        "LastWriteTime":  "\/Date(1780309808894)\/"
    },
    {
        "FullName":  "D:\\temp\\RUCxiaolaba-Advanced-Search\\data\\railway_rescue\\20260601-144118\\feedback.jsonl",
        "Length":  5,
        "LastWriteTime":  "\/Date(1780296084048)\/"
    },
    {
        "FullName":  "D:\\temp\\RUCxiaolaba-Advanced-Search\\data\\railway_sync\\20260601-233001\\feedback.jsonl",
        "Length":  5,
        "LastWriteTime":  "\/Date(1780327807791)\/"
    },
    {
        "FullName":  "D:\\temp\\RUCxiaolaba-Advanced-Search\\data\\railway_sync\\20260601-223002\\feedback.jsonl",
        "Length":  5,
        "LastWriteTime":  "\/Date(1780324203205)\/"
    },
    {
        "FullName":  "D:\\temp\\RUCxiaolaba-Advanced-Search\\data\\railway_sync\\20260601-173002\\feedback.jsonl",
        "Length":  0,
        "LastWriteTime":  "\/Date(1780306207933)\/"
    },
    {
        "FullName":  "D:\\temp\\RUCxiaolaba-Advanced-Search\\data\\railway_sync\\20260602-013002\\feedback.jsonl",
        "Length":  0,
        "LastWriteTime":  "\/Date(1780335009478)\/"
    },
    {
        "FullName":  "D:\\temp\\RUCxiaolaba-Advanced-Search\\data\\railway_sync\\20260601-163002\\feedback.jsonl",
        "Length":  0,
        "LastWriteTime":  "\/Date(1780302608498)\/"
    },
    {
        "FullName":  "D:\\temp\\RUCxiaolaba-Advanced-Search\\data\\railway_sync\\20260602-103003\\feedback.jsonl",
        "Length":  0,
        "LastWriteTime":  "\/Date(1780367410247)\/"
    },
    {
        "FullName":  "D:\\temp\\RUCxiaolaba-Advanced-Search\\data\\railway_sync\\20260602-023001\\feedback.jsonl",
        "Length":  0,
        "LastWriteTime":  "\/Date(1780338607985)\/"
    },
    {
        "FullName":  "D:\\temp\\RUCxiaolaba-Advanced-Search\\data\\railway_sync\\20260601-213002\\feedback.jsonl",
        "Length":  0,
        "LastWriteTime":  "\/Date(1780320612444)\/"
    },
    {
        "FullName":  "D:\\temp\\RUCxiaolaba-Advanced-Search\\data\\railway_sync\\20260602-003001\\feedback.jsonl",
        "Length":  0,
        "LastWriteTime":  "\/Date(1780331408177)\/"
    },
    {
        "FullName":  "D:\\temp\\RUCxiaolaba-Advanced-Search\\data\\railway_sync\\20260601-203002\\feedback.jsonl",
        "Length":  0,
        "LastWriteTime":  "\/Date(1780317009759)\/"
    },
    {
        "FullName":  "D:\\temp\\RUCxiaolaba-Advanced-Search\\data\\railway_sync\\20260602-101249\\feedback.jsonl",
        "Length":  0,
        "LastWriteTime":  "\/Date(1780366374585)\/"
    },
    {
        "FullName":  "D:\\temp\\RUCxiaolaba-Advanced-Search\\data\\railway_sync\\20260602-033350\\feedback.jsonl",
        "Length":  0,
        "LastWriteTime":  "\/Date(1780366096745)\/"
    },
    {
        "FullName":  "D:\\temp\\RUCxiaolaba-Advanced-Search\\data\\railway_sync\\20260601-194026\\feedback.jsonl",
        "Length":  0,
        "LastWriteTime":  "\/Date(1780314041594)\/"
    },
    {
        "FullName":  "D:\\temp\\RUCxiaolaba-Advanced-Search\\data\\railway_rescue\\20260601-144118\\checkin_count.json",
        "Length":  0,
        "LastWriteTime":  "\/Date(1780296282769)\/"
    },
    {
        "FullName":  "D:\\temp\\RUCxiaolaba-Advanced-Search\\data\\railway_sync\\20260602-113002\\feedback.jsonl",
        "Length":  0,
        "LastWriteTime":  "\/Date(1780371009285)\/"
    },
    {
        "FullName":  "D:\\temp\\RUCxiaolaba-Advanced-Search\\data\\railway_rescue\\20260601-142011\\feedback.jsonl",
        "Length":  0,
        "LastWriteTime":  "\/Date(1780294812189)\/"
    },
    {
        "FullName":  "D:\\temp\\RUCxiaolaba-Advanced-Search\\data\\railway_rescue\\20260601-142011\\checkin_count.json",
        "Length":  0,
        "LastWriteTime":  "\/Date(1780294814230)\/"
    },
    {
        "FullName":  "D:\\temp\\RUCxiaolaba-Advanced-Search\\data\\railway_sync\\20260601-144828\\feedback.jsonl",
        "Length":  0,
        "LastWriteTime":  "\/Date(1780296515438)\/"
    },
    {
        "FullName":  "D:\\temp\\RUCxiaolaba-Advanced-Search\\data\\railway_sync\\20260601-153001\\feedback.jsonl",
        "Length":  0,
        "LastWriteTime":  "\/Date(1780299009774)\/"
    },
    {
        "FullName":  "D:\\temp\\RUCxiaolaba-Advanced-Search\\data\\railway_sync\\feedback.latest.jsonl",
        "Length":  0,
        "LastWriteTime":  "\/Date(1780371009285)\/"
    },
    {
        "FullName":  "D:\\temp\\RUCxiaolaba-Advanced-Search\\data\\railway_sync\\20260601-144603\\feedback.jsonl",
        "Length":  0,
        "LastWriteTime":  "\/Date(1780296368151)\/"
    },
    {
        "FullName":  "D:\\temp\\RUCxiaolaba-Advanced-Search\\data\\railway_sync\\20260601-173002",
        "Length":  null,
        "LastWriteTime":  "\/Date(1780306213142)\/"
    },
    {
        "FullName":  "D:\\temp\\RUCxiaolaba-Advanced-Search\\data\\railway_sync\\20260601-163002",
        "Length":  null,
        "LastWriteTime":  "\/Date(1780302614027)\/"
    },
    {
        "FullName":  "D:\\temp\\RUCxiaolaba-Advanced-Search\\data\\railway_sync\\20260601-153001",
        "Length":  null,
        "LastWriteTime":  "\/Date(1780299015183)\/"
    },
    {
        "FullName":  "D:\\temp\\RUCxiaolaba-Advanced-Search\\data\\railway_sync\\20260601-144828",
        "Length":  null,
        "LastWriteTime":  "\/Date(1780296525534)\/"
    },
    {
        "FullName":  "D:\\temp\\RUCxiaolaba-Advanced-Search\\data\\railway_sync\\20260601-144603",
        "Length":  null,
        "LastWriteTime":  "\/Date(1780296373540)\/"
    },
    {
        "FullName":  "D:\\temp\\RUCxiaolaba-Advanced-Search\\data\\railway_sync",
        "Length":  null,
        "LastWriteTime":  "\/Date(1780371003066)\/"
    },
    {
        "FullName":  "D:\\temp\\RUCxiaolaba-Advanced-Search\\data\\railway_rescue",
        "Length":  null,
        "LastWriteTime":  "\/Date(1780296078468)\/"
    },
    {
        "FullName":  "D:\\temp\\RUCxiaolaba-Advanced-Search\\data\\railway_rescue\\20260601-144118",
        "Length":  null,
        "LastWriteTime":  "\/Date(1780296196394)\/"
    },
    {
        "FullName":  "D:\\temp\\RUCxiaolaba-Advanced-Search\\data\\railway_rescue\\20260601-142011",
        "Length":  null,
        "LastWriteTime":  "\/Date(1780294814230)\/"
    },
    {
        "FullName":  "D:\\temp\\RUCxiaolaba-Advanced-Search\\data\\railway_sync\\20260601-183007",
        "Length":  null,
        "LastWriteTime":  "\/Date(1780309821631)\/"
    },
    {
        "FullName":  "D:\\temp\\RUCxiaolaba-Advanced-Search\\data\\railway_sync\\20260602-033350",
        "Length":  null,
        "LastWriteTime":  "\/Date(1780366105446)\/"
    },
    {
        "FullName":  "D:\\temp\\RUCxiaolaba-Advanced-Search\\data\\railway_sync\\20260602-023001",
        "Length":  null,
        "LastWriteTime":  "\/Date(1780338613590)\/"
    },
    {
        "FullName":  "D:\\temp\\RUCxiaolaba-Advanced-Search\\data\\railway_sync\\20260602-013002",
        "Length":  null,
        "LastWriteTime":  "\/Date(1780335015561)\/"
    },
    {
        "FullName":  "D:\\temp\\RUCxiaolaba-Advanced-Search\\data\\railway_sync\\20260602-113002",
        "Length":  null,
        "LastWriteTime":  "\/Date(1780371015394)\/"
    },
    {
        "FullName":  "D:\\temp\\RUCxiaolaba-Advanced-Search\\data\\railway_sync\\20260602-103003",
        "Length":  null,
        "LastWriteTime":  "\/Date(1780367416700)\/"
    },
    {
        "FullName":  "D:\\temp\\RUCxiaolaba-Advanced-Search\\data\\railway_sync\\20260602-101249",
        "Length":  null,
        "LastWriteTime":  "\/Date(1780366383239)\/"
    },
    {
        "FullName":  "D:\\temp\\RUCxiaolaba-Advanced-Search\\data\\railway_sync\\20260601-213002",
        "Length":  null,
        "LastWriteTime":  "\/Date(1780320617973)\/"
    },
    {
        "FullName":  "D:\\temp\\RUCxiaolaba-Advanced-Search\\data\\railway_sync\\20260601-203002",
        "Length":  null,
        "LastWriteTime":  "\/Date(1780317015374)\/"
    },
    {
        "FullName":  "D:\\temp\\RUCxiaolaba-Advanced-Search\\data\\railway_sync\\20260601-194026",
        "Length":  null,
        "LastWriteTime":  "\/Date(1780314050304)\/"
    },
    {
        "FullName":  "D:\\temp\\RUCxiaolaba-Advanced-Search\\data\\railway_sync\\20260602-003001",
        "Length":  null,
        "LastWriteTime":  "\/Date(1780331415528)\/"
    },
    {
        "FullName":  "D:\\temp\\RUCxiaolaba-Advanced-Search\\data\\railway_sync\\20260601-233001",
        "Length":  null,
        "LastWriteTime":  "\/Date(1780327812854)\/"
    },
    {
        "FullName":  "D:\\temp\\RUCxiaolaba-Advanced-Search\\data\\railway_sync\\20260601-223002",
        "Length":  null,
        "LastWriteTime":  "\/Date(1780324203579)\/"
    }
]
